mango/__init__.py
mango/domain/__init__.py
mango/domain/distribution.py
mango/domain/domain_space.py
mango/domain/parameter_sampler.py
mango/metatuner.py
mango/optimizer/__init__.py
mango/optimizer/base_predictor.py
mango/optimizer/bayesian_learning.py
mango/scheduler.py
mango/tuner.py
arm_mango-1.5.1.dist-info/LICENSE
arm_mango-1.5.1.dist-info/METADATA
arm_mango-1.5.1.dist-info/WHEEL
arm_mango-1.5.1.dist-info/RECORD
