Metadata-Version: 2.1
Name: arm-mango
Version: 1.5.1
Summary: parallel bayesian optimization over complex search spaces
Home-page: https://github.com/ARM-software/mango
License: Apache-2.0
Author: Sandeep Singh Sandha
Author-email: sandha.iitr@gmail.com
Requires-Python: >=3.10
Classifier: License :: OSI Approved :: Apache Software License
Classifier: Programming Language :: Python :: 3
Classifier: Programming Language :: Python :: 3.10
Classifier: Programming Language :: Python :: 3.11
Classifier: Programming Language :: Python :: 3
Requires-Dist: numpy (>=1.17.0)
Requires-Dist: scikit_learn (>=0.21.3)
Requires-Dist: scipy (>=1.4.1)
Requires-Dist: tqdm (>=4.36.1)
Project-URL: Repository, https://github.com/ARM-software/mango
